{
    "$schema": "https://smapi.io/schemas/content-patcher.json",
    "Changes": [
        // ---------
        // Custom Location Definitions 
        // (alphabetical name then clockwise direction)
        // ---------

        // ---------
        // Vanilla Location Edits 
        // (alphabetical name then clockwise direction)
        // ---------
        
        // FIXME: needs doing entirely
        {
            "Action": "EditMap",
            "Target": "Maps/SecretWoods",
            "FromFile": "Assets/Maps/SecretWoodRight.tmx",
            "ToArea": {
                "X": 0,
                "Y": 0,
                "Width": 0,
                "Height": 0
            }
        },
        // FIXME: Same here
        {
            "Action": "EditMap",
            "Target": "Maps/SecretWoods",
            "FromFile": "Assets/Maps/SecretWoodBottom.tmx",
            "ToArea": {
                "X": 0,
                "Y": 0,
                "Width": 0,
                "Height": 0
            }
        },

        // ---------
        // Custom Location Edits 
        // (alphabetical name then clockwise direction)
        // ---------

    ]
}


